odoo/addons/mgmtsystem_action_template/README.rst
odoo/addons/mgmtsystem_action_template/__init__.py
odoo/addons/mgmtsystem_action_template/__manifest__.py
odoo/addons/mgmtsystem_action_template/i18n/es.po
odoo/addons/mgmtsystem_action_template/i18n/it.po
odoo/addons/mgmtsystem_action_template/i18n/mgmtsystem_action_template.pot
odoo/addons/mgmtsystem_action_template/models/__init__.py
odoo/addons/mgmtsystem_action_template/models/mgmtsystem_action.py
odoo/addons/mgmtsystem_action_template/models/mgmtsystem_action_template.py
odoo/addons/mgmtsystem_action_template/readme/CONTRIBUTORS.md
odoo/addons/mgmtsystem_action_template/readme/DESCRIPTION.md
odoo/addons/mgmtsystem_action_template/readme/HISTORY.md
odoo/addons/mgmtsystem_action_template/readme/USAGE.md
odoo/addons/mgmtsystem_action_template/security/ir.model.access.csv
odoo/addons/mgmtsystem_action_template/static/description/icon.png
odoo/addons/mgmtsystem_action_template/static/description/index.html
odoo/addons/mgmtsystem_action_template/tests/__init__.py
odoo/addons/mgmtsystem_action_template/tests/test_action_template.py
odoo/addons/mgmtsystem_action_template/views/mgmtsystem_action_template.xml
odoo/addons/mgmtsystem_action_template/views/mgmtsystem_action_views.xml
odoo_addon_mgmtsystem_action_template-18.0.1.0.0.3.dist-info/METADATA
odoo_addon_mgmtsystem_action_template-18.0.1.0.0.3.dist-info/WHEEL
odoo_addon_mgmtsystem_action_template-18.0.1.0.0.3.dist-info/top_level.txt
odoo_addon_mgmtsystem_action_template-18.0.1.0.0.3.dist-info/RECORD
